Workbook

Sheet Tracker
A1: Rental Income & Expense Tracker
A2: Property: | B2: 123 Example St | H2: Tax year: | I2: 2026
A3: Sample data shown — clear the blue cells and enter your own. Totals update automatically.
A4: Category | B4: Jan | C4: Feb | D4: Mar | E4: Apr | F4: May | G4: Jun | H4: Jul | I4: Aug | J4: Sep | K4: Oct | L4: Nov | M4: Dec | N4: Total
A5: INCOME
A6: Rent | B6: 1500 | C6: 1500 | D6: 1500 | E6: 1500 | F6: 1500 | G6: 1500 | H6: 1500 | I6: 1500 | J6: 1500 | K6: 1500 | L6: 1500 | M6: 1500 | N6: =SUM(B6:M6)
A7: Other income (late fees, laundry, parking) | B7: 50 | C7: 50 | D7: 50 | E7: 50 | F7: 50 | G7: 50 | H7: 50 | I7: 50 | J7: 50 | K7: 50 | L7: 50 | M7: 50 | N7: =SUM(B7:M7)
A8: Total income | B8: =SUM(B6:B7) | C8: =SUM(C6:C7) | D8: =SUM(D6:D7) | E8: =SUM(E6:E7) | F8: =SUM(F6:F7) | G8: =SUM(G6:G7) | H8: =SUM(H6:H7) | I8: =SUM(I6:I7) | ... N8: =SUM(N6:N7)
A9: EXPENSES (IRS Schedule E categories)
A10: Advertising | B10: 0 | C10: 0 | D10: 0 | E10: 0 | F10: 0 | G10: 0 | H10: 0 | I10: 0 | J10: 0 | K10: 0 | L10: 0 | M10: 0 | N10: =SUM(B10:M10)
A11: Auto & travel | B11: 0 | C11: 0 | D11: 0 | E11: 0 | F11: 0 | G11: 0 | H11: 0 | I11: 0 | J11: 0 | K11: 0 | L11: 0 | M11: 0 | N11: =SUM(B11:M11)
A12: Cleaning & maintenance | B12: 0 | C12: 0 | D12: 0 | E12: 0 | F12: 0 | G12: 0 | H12: 0 | I12: 0 | J12: 0 | K12: 0 | L12: 0 | M12: 0 | N12: =SUM(B12:M12)
A13: Commissions | B13: 0 | C13: 0 | D13: 0 | E13: 0 | F13: 0 | G13: 0 | H13: 0 | I13: 0 | J13: 0 | K13: 0 | L13: 0 | M13: 0 | N13: =SUM(B13:M13)
A14: Insurance | B14: 100 | C14: 100 | D14: 100 | E14: 100 | F14: 100 | G14: 100 | H14: 100 | I14: 100 | J14: 100 | K14: 100 | L14: 100 | M14: 100 | N14: =SUM(B14:M14)
A15: Legal & professional fees | B15: 0 | C15: 0 | D15: 0 | E15: 0 | F15: 0 | G15: 0 | H15: 0 | I15: 0 | J15: 0 | K15: 0 | L15: 0 | M15: 0 | N15: =SUM(B15:M15)
A16: Management fees | B16: 150 | C16: 150 | D16: 150 | E16: 150 | F16: 150 | G16: 150 | H16: 150 | I16: 150 | J16: 150 | K16: 150 | L16: 150 | M16: 150 | N16: =SUM(B16:M16)
A17: Mortgage interest | B17: 700 | C17: 700 | D17: 700 | E17: 700 | F17: 700 | G17: 700 | H17: 700 | I17: 700 | J17: 700 | K17: 700 | L17: 700 | M17: 700 | N17: =SUM(B17:M17)
A18: Repairs | B18: 80 | C18: 80 | D18: 80 | E18: 80 | F18: 80 | G18: 80 | H18: 80 | I18: 80 | J18: 80 | K18: 80 | L18: 80 | M18: 80 | N18: =SUM(B18:M18)
A19: Supplies | B19: 20 | C19: 20 | D19: 20 | E19: 20 | F19: 20 | G19: 20 | H19: 20 | I19: 20 | J19: 20 | K19: 20 | L19: 20 | M19: 20 | N19: =SUM(B19:M19)
A20: Property taxes | B20: 250 | C20: 250 | D20: 250 | E20: 250 | F20: 250 | G20: 250 | H20: 250 | I20: 250 | J20: 250 | K20: 250 | L20: 250 | M20: 250 | N20: =SUM(B20:M20)
A21: Utilities | B21: 60 | C21: 60 | D21: 60 | E21: 60 | F21: 60 | G21: 60 | H21: 60 | I21: 60 | J21: 60 | K21: 60 | L21: 60 | M21: 60 | N21: =SUM(B21:M21)
A22: Other | B22: 0 | C22: 0 | D22: 0 | E22: 0 | F22: 0 | G22: 0 | H22: 0 | I22: 0 | J22: 0 | K22: 0 | L22: 0 | M22: 0 | N22: =SUM(B22:M22)
A23: Total expenses | B23: =SUM(B10:B22) | C23: =SUM(C10:C22) | D23: =SUM(D10:D22) | E23: =SUM(E10:E22) | F23: =SUM(F10:F22) | G23: =SUM(G10:G22) | H23: =SUM(H10:H22) | I23: =SUM(I10:I22) | ... N23: =SUM(N10:N22)
A24: NET CASH FLOW | B24: =B8-B23 | C24: =C8-C23 | D24: =D8-D23 | E24: =E8-E23 | F24: =F8-F23 | G24: =G8-G23 | H24: =H8-H23 | I24: =I8-I23 | ... N24: =N8-N23

Sheet Summary
A1: Annual Summary
A3: Total income | B3: =Tracker!N8
A4: Total expenses | B4: =Tracker!N23
A5: Net operating cash flow | B5: =Tracker!N24
A7: Cash invested (for cash-on-cash) | B7: 46000
A8: Cash-on-cash return | B8: =IF(B7=0,0,B5/B7)
A10: Expense breakdown
A11: Category | B11: Annual | C11: % of exp
A12: Advertising | B12: =Tracker!N10 | C12: =IF(B4=0,0,Tracker!N10/B4)
A13: Auto & travel | B13: =Tracker!N11 | C13: =IF(B4=0,0,Tracker!N11/B4)
A14: Cleaning & maintenance | B14: =Tracker!N12 | C14: =IF(B4=0,0,Tracker!N12/B4)
A15: Commissions | B15: =Tracker!N13 | C15: =IF(B4=0,0,Tracker!N13/B4)
A16: Insurance | B16: =Tracker!N14 | C16: =IF(B4=0,0,Tracker!N14/B4)
A17: Legal & professional fees | B17: =Tracker!N15 | C17: =IF(B4=0,0,Tracker!N15/B4)
A18: Management fees | B18: =Tracker!N16 | C18: =IF(B4=0,0,Tracker!N16/B4)
A19: Mortgage interest | B19: =Tracker!N17 | C19: =IF(B4=0,0,Tracker!N17/B4)
A20: Repairs | B20: =Tracker!N18 | C20: =IF(B4=0,0,Tracker!N18/B4)
A21: Supplies | B21: =Tracker!N19 | C21: =IF(B4=0,0,Tracker!N19/B4)
A22: Property taxes | B22: =Tracker!N20 | C22: =IF(B4=0,0,Tracker!N20/B4)
A23: Utilities | B23: =Tracker!N21 | C23: =IF(B4=0,0,Tracker!N21/B4)
A24: Other | B24: =Tracker!N22 | C24: =IF(B4=0,0,Tracker!N22/B4)
A26: These categories follow IRS Schedule E lines — export or hand to your
A27: accountant at tax time. For organization only; not tax advice.
